README.rst
setup.py
docmongo/__init__.py
docmongo/decorator.py
docmongo/delegate.py
docmongo/document.py
docmongo/exceptions.py
docmongo/fields.py
docmongo/interfaces.py
docmongo.egg-info/PKG-INFO
docmongo.egg-info/SOURCES.txt
docmongo.egg-info/dependency_links.txt
docmongo.egg-info/not-zip-safe
docmongo.egg-info/requires.txt
docmongo.egg-info/top_level.txt
docmongo/tests/__init__.py
docmongo/tests/test_delegate.py
docmongo/tests/test_document.py
docmongo/tests/test_example.py
docmongo/tests/test_fields.py