Metadata-Version: 1.1
Name: docmongo
Version: 1.0.0
Summary: A high abastract architecture with pymongo
Home-page: https://github.com/satoshun/docmongo
Author: Sato Shun
Author-email: shun.sato1@gmail.com
License: Apache License, Version 2.0
Keywords: mongodb,mongo,pymongo
Platform: UNKNOWN
Classifier: Programming Language :: Python :: 3
Classifier: Programming Language :: Python :: 3.2
Classifier: Programming Language :: Python :: 3.3
